bouter/__init__.py
bouter/angles.py
bouter/bout_stats.py
bouter/decorators.py
bouter/descriptors.py
bouter/df_utilities.py
bouter/experiment.py
bouter/multisession_exp.py
bouter/utilities.py
bouter/embedded/__init__.py
bouter/free/__init__.py
bouter/tests/__init__.py
bouter/tests/_create_assets.py
bouter/tests/conftest.py
bouter/tests/test_angle_utils.py
bouter/tests/test_bouter.py
bouter/tests/test_embedded.py
bouter/tests/test_free.py
bouter/tests/test_utilities.py
bouter/tests/assets/embedded_dataset/192316_behavior_log.hdf5
bouter/tests/assets/embedded_dataset/192316_estimator_log.hdf5
bouter/tests/assets/embedded_dataset/192316_metadata.json
bouter/tests/assets/embedded_dataset/192316_stimulus_log.hdf5
bouter/tests/assets/embedded_dataset/expected_vigor.h5
bouter/tests/assets/eyes_dataset/093151_behavior_log.hdf5
bouter/tests/assets/eyes_dataset/093151_metadata.json
bouter/tests/assets/eyes_dataset/093151_stimulus_log.hdf5
bouter/tests/assets/freely_swimming_dataset/162934_behavior_log.hdf5
bouter/tests/assets/freely_swimming_dataset/162934_metadata.json
bouter/tests/assets/freely_swimming_dataset/162934_stimulus_log.hdf5
bouter/tests/assets/freely_swimming_dataset/test_extracted_bouts.h5
bouter-0.2.0.dist-info/AUTHORS.rst
bouter-0.2.0.dist-info/LICENSE
bouter-0.2.0.dist-info/METADATA
bouter-0.2.0.dist-info/WHEEL
bouter-0.2.0.dist-info/top_level.txt
bouter-0.2.0.dist-info/RECORD
